{
  "annotations": {
    "list": [
      {
        "builtIn": 1,
        "datasource": "-- Grafana --",
        "enable": true,
        "hide": true,
        "iconColor": "rgba(0, 211, 255, 1)",
        "name": "Annotations & Alerts",
        "target": {
          "limit": 100,
          "matchAny": false,
          "tags": [],
          "type": "dashboard"
        },
        "type": "dashboard"
      }
    ]
  },
  "editable": true,
  "fiscalYearStartMonth": 0,
  "gnetId": null,
  "graphTooltip": 0,
  "links": [],
  "liveNow": true,
  "panels": [
    {
      "collapsed": false,
      "datasource": null,
      "gridPos": {
        "h": 1,
        "w": 24,
        "x": 0,
        "y": 0
      },
      "id": 16,
      "panels": [],
      "title": "Summary",
      "type": "row"
    },
    {
      "datasource": null,
      "fieldConfig": {
        "defaults": {
          "color": {
            "mode": "thresholds",
            "seriesBy": "last"
          },
          "custom": {
            "axisGridShow": true,
            "axisLabel": "",
            "axisPlacement": "left",
            "barAlignment": 0,
            "drawStyle": "line",
            "fillOpacity": 7,
            "gradientMode": "hue",
            "hideFrom": {
              "legend": false,
              "tooltip": false,
              "viz": false
            },
            "lineInterpolation": "linear",
            "lineStyle": {
              "fill": "solid"
            },
            "lineWidth": 1,
            "pointSize": 3,
            "scaleDistribution": {
              "type": "linear"
            },
            "showPoints": "always",
            "spanNulls": true,
            "stacking": {
              "group": "A",
              "mode": "normal"
            },
            "thresholdsStyle": {
              "mode": "off"
            }
          },
          "decimals": 0,
          "displayName": "Performance score",
          "mappings": [],
          "max": 1,
          "min": 0,
          "thresholds": {
            "mode": "percentage",
            "steps": [
              {
                "color": "blue",
                "value": null
              },
              {
                "color": "semi-dark-red",
                "value": 0
              },
              {
                "color": "orange",
                "value": 49
              },
              {
                "color": "semi-dark-green",
                "value": 89
              }
            ]
          },
          "unit": "percentunit"
        },
        "overrides": []
      },
      "gridPos": {
        "h": 8,
        "w": 8,
        "x": 0,
        "y": 1
      },
      "id": 4,
      "options": {
        "legend": {
          "calcs": [
            "min",
            "max",
            "mean"
          ],
          "displayMode": "table",
          "placement": "bottom"
        },
        "tooltip": {
          "mode": "single"
        }
      },
      "targets": [
        {
          "query": "from(bucket: \"lighthouse\")\r\n  |> range(start: v.timeRangeStart, stop: v.timeRangeStop)\r\n  |> filter(fn: (r) => r[\"_measurement\"] == \"performance-score\")\r\n  |> filter(fn: (r) => r[\"_field\"] == \"performance-score\")\r\n  |> filter(fn: (r) => r[\"host\"] == \"host1\")\r\n  |> filter(fn: (r) => r[\"url\"] == \"${url}\")",
          "refId": "A"
        }
      ],
      "title": "Performance score",
      "transparent": true,
      "type": "timeseries"
    },
    {
      "datasource": null,
      "fieldConfig": {
        "defaults": {
          "color": {
            "mode": "thresholds",
            "seriesBy": "last"
          },
          "custom": {
            "axisGridShow": true,
            "axisLabel": "",
            "axisPlacement": "left",
            "barAlignment": 0,
            "drawStyle": "line",
            "fillOpacity": 7,
            "gradientMode": "hue",
            "hideFrom": {
              "legend": false,
              "tooltip": false,
              "viz": false
            },
            "lineInterpolation": "linear",
            "lineStyle": {
              "fill": "solid"
            },
            "lineWidth": 1,
            "pointSize": 3,
            "scaleDistribution": {
              "type": "linear"
            },
            "showPoints": "always",
            "spanNulls": true,
            "stacking": {
              "group": "A",
              "mode": "normal"
            },
            "thresholdsStyle": {
              "mode": "off"
            }
          },
          "decimals": 0,
          "displayName": "Best practice score",
          "mappings": [],
          "max": 1,
          "min": 0,
          "thresholds": {
            "mode": "percentage",
            "steps": [
              {
                "color": "blue",
                "value": null
              },
              {
                "color": "semi-dark-red",
                "value": 0
              },
              {
                "color": "orange",
                "value": 49
              },
              {
                "color": "semi-dark-green",
                "value": 89
              }
            ]
          },
          "unit": "percentunit"
        },
        "overrides": []
      },
      "gridPos": {
        "h": 8,
        "w": 8,
        "x": 8,
        "y": 1
      },
      "id": 6,
      "options": {
        "legend": {
          "calcs": [
            "min",
            "max",
            "mean"
          ],
          "displayMode": "table",
          "placement": "bottom"
        },
        "tooltip": {
          "mode": "single"
        }
      },
      "targets": [
        {
          "query": "from(bucket: \"lighthouse\")\r\n  |> range(start: v.timeRangeStart, stop: v.timeRangeStop)\r\n  |> filter(fn: (r) => r[\"_measurement\"] == \"best-practices-score\")\r\n  |> filter(fn: (r) => r[\"_field\"] == \"best-practices-score\")\r\n  |> filter(fn: (r) => r[\"host\"] == \"host1\")\r\n  |> filter(fn: (r) => r[\"url\"] == \"${url}\")",
          "refId": "A"
        }
      ],
      "title": "Best practice score",
      "transparent": true,
      "type": "timeseries"
    },
    {
      "datasource": null,
      "fieldConfig": {
        "defaults": {
          "color": {
            "mode": "thresholds",
            "seriesBy": "last"
          },
          "custom": {
            "axisGridShow": true,
            "axisLabel": "",
            "axisPlacement": "left",
            "barAlignment": 0,
            "drawStyle": "line",
            "fillOpacity": 7,
            "gradientMode": "hue",
            "hideFrom": {
              "legend": false,
              "tooltip": false,
              "viz": false
            },
            "lineInterpolation": "linear",
            "lineStyle": {
              "fill": "solid"
            },
            "lineWidth": 1,
            "pointSize": 3,
            "scaleDistribution": {
              "type": "linear"
            },
            "showPoints": "always",
            "spanNulls": true,
            "stacking": {
              "group": "A",
              "mode": "normal"
            },
            "thresholdsStyle": {
              "mode": "off"
            }
          },
          "decimals": 0,
          "displayName": "Accessibility Score",
          "mappings": [],
          "max": 1,
          "min": 0,
          "thresholds": {
            "mode": "percentage",
            "steps": [
              {
                "color": "blue",
                "value": null
              },
              {
                "color": "semi-dark-red",
                "value": 0
              },
              {
                "color": "orange",
                "value": 49
              },
              {
                "color": "semi-dark-green",
                "value": 89
              }
            ]
          },
          "unit": "percentunit"
        },
        "overrides": []
      },
      "gridPos": {
        "h": 8,
        "w": 8,
        "x": 16,
        "y": 1
      },
      "id": 8,
      "options": {
        "legend": {
          "calcs": [
            "min",
            "max",
            "mean"
          ],
          "displayMode": "table",
          "placement": "bottom"
        },
        "tooltip": {
          "mode": "single"
        }
      },
      "targets": [
        {
          "query": "from(bucket: \"lighthouse\")\r\n  |> range(start: v.timeRangeStart, stop: v.timeRangeStop)\r\n  |> filter(fn: (r) => r[\"_measurement\"] == \"accessibility-score\")\r\n  |> filter(fn: (r) => r[\"_field\"] == \"accessibility-score\")\r\n  |> filter(fn: (r) => r[\"host\"] == \"host1\")\r\n  |> filter(fn: (r) => r[\"url\"] == \"${url}\")",
          "refId": "A"
        }
      ],
      "title": "Accessibility Score",
      "transparent": true,
      "type": "timeseries"
    },
    {
      "datasource": null,
      "fieldConfig": {
        "defaults": {
          "color": {
            "mode": "thresholds",
            "seriesBy": "last"
          },
          "custom": {
            "axisGridShow": true,
            "axisLabel": "",
            "axisPlacement": "left",
            "barAlignment": 0,
            "drawStyle": "line",
            "fillOpacity": 7,
            "gradientMode": "hue",
            "hideFrom": {
              "legend": false,
              "tooltip": false,
              "viz": false
            },
            "lineInterpolation": "linear",
            "lineStyle": {
              "fill": "solid"
            },
            "lineWidth": 1,
            "pointSize": 3,
            "scaleDistribution": {
              "type": "linear"
            },
            "showPoints": "always",
            "spanNulls": true,
            "stacking": {
              "group": "A",
              "mode": "normal"
            },
            "thresholdsStyle": {
              "mode": "off"
            }
          },
          "decimals": 0,
          "displayName": "SEO score",
          "mappings": [],
          "max": 1,
          "min": 0,
          "thresholds": {
            "mode": "percentage",
            "steps": [
              {
                "color": "blue",
                "value": null
              },
              {
                "color": "semi-dark-red",
                "value": 0
              },
              {
                "color": "orange",
                "value": 49
              },
              {
                "color": "semi-dark-green",
                "value": 89
              }
            ]
          },
          "unit": "percentunit"
        },
        "overrides": []
      },
      "gridPos": {
        "h": 8,
        "w": 8,
        "x": 4,
        "y": 9
      },
      "id": 10,
      "options": {
        "legend": {
          "calcs": [
            "min",
            "max",
            "mean"
          ],
          "displayMode": "table",
          "placement": "bottom"
        },
        "tooltip": {
          "mode": "single"
        }
      },
      "targets": [
        {
          "query": "from(bucket: \"lighthouse\")\r\n  |> range(start: v.timeRangeStart, stop: v.timeRangeStop)\r\n  |> filter(fn: (r) => r[\"_measurement\"] == \"seo-score\")\r\n  |> filter(fn: (r) => r[\"_field\"] == \"seo-score\")\r\n  |> filter(fn: (r) => r[\"host\"] == \"host1\")\r\n  |> filter(fn: (r) => r[\"url\"] == \"${url}\")",
          "refId": "A"
        }
      ],
      "title": "SEO score",
      "transparent": true,
      "type": "timeseries"
    },
    {
      "datasource": null,
      "fieldConfig": {
        "defaults": {
          "color": {
            "mode": "thresholds",
            "seriesBy": "last"
          },
          "custom": {
            "axisGridShow": true,
            "axisLabel": "",
            "axisPlacement": "left",
            "barAlignment": 0,
            "drawStyle": "line",
            "fillOpacity": 7,
            "gradientMode": "hue",
            "hideFrom": {
              "legend": false,
              "tooltip": false,
              "viz": false
            },
            "lineInterpolation": "linear",
            "lineStyle": {
              "fill": "solid"
            },
            "lineWidth": 1,
            "pointSize": 3,
            "scaleDistribution": {
              "type": "linear"
            },
            "showPoints": "always",
            "spanNulls": true,
            "stacking": {
              "group": "A",
              "mode": "normal"
            },
            "thresholdsStyle": {
              "mode": "off"
            }
          },
          "decimals": 0,
          "displayName": "Performance score",
          "mappings": [],
          "max": 1,
          "min": 0,
          "thresholds": {
            "mode": "percentage",
            "steps": [
              {
                "color": "blue",
                "value": null
              },
              {
                "color": "semi-dark-red",
                "value": 0
              },
              {
                "color": "orange",
                "value": 49
              },
              {
                "color": "semi-dark-green",
                "value": 89
              }
            ]
          },
          "unit": "percentunit"
        },
        "overrides": []
      },
      "gridPos": {
        "h": 8,
        "w": 8,
        "x": 12,
        "y": 9
      },
      "id": 12,
      "options": {
        "legend": {
          "calcs": [
            "min",
            "max",
            "mean"
          ],
          "displayMode": "table",
          "placement": "bottom"
        },
        "tooltip": {
          "mode": "single"
        }
      },
      "targets": [
        {
          "query": "from(bucket: \"lighthouse\")\r\n  |> range(start: v.timeRangeStart, stop: v.timeRangeStop)\r\n  |> filter(fn: (r) => r[\"_measurement\"] == \"pwa-score\")\r\n  |> filter(fn: (r) => r[\"_field\"] == \"pwa-score\")\r\n  |> filter(fn: (r) => r[\"host\"] == \"host1\")\r\n  |> filter(fn: (r) => r[\"url\"] == \"${url}\")",
          "refId": "A"
        }
      ],
      "title": "PWA score",
      "transparent": true,
      "type": "timeseries"
    },
    {
      "collapsed": false,
      "datasource": null,
      "gridPos": {
        "h": 1,
        "w": 24,
        "x": 0,
        "y": 17
      },
      "id": 14,
      "panels": [],
      "title": "Performance Metrics (Lower is better)",
      "type": "row"
    },
    {
      "datasource": null,
      "description": "First Contentful Paint marks the time at which the first text or image is painted.",
      "fieldConfig": {
        "defaults": {
          "color": {
            "mode": "palette-classic"
          },
          "custom": {
            "axisLabel": "",
            "axisPlacement": "auto",
            "barAlignment": 0,
            "drawStyle": "line",
            "fillOpacity": 0,
            "gradientMode": "none",
            "hideFrom": {
              "legend": false,
              "tooltip": false,
              "viz": false
            },
            "lineInterpolation": "linear",
            "lineWidth": 1,
            "pointSize": 5,
            "scaleDistribution": {
              "type": "linear"
            },
            "showPoints": "auto",
            "spanNulls": false,
            "stacking": {
              "group": "A",
              "mode": "none"
            },
            "thresholdsStyle": {
              "mode": "off"
            }
          },
          "mappings": [],
          "thresholds": {
            "mode": "absolute",
            "steps": [
              {
                "color": "green",
                "value": null
              },
              {
                "color": "red",
                "value": 80
              }
            ]
          }
        },
        "overrides": []
      },
      "gridPos": {
        "h": 8,
        "w": 12,
        "x": 0,
        "y": 18
      },
      "id": 20,
      "options": {
        "legend": {
          "calcs": [],
          "displayMode": "list",
          "placement": "bottom"
        },
        "tooltip": {
          "mode": "single"
        }
      },
      "targets": [
        {
          "query": "from(bucket: \"lighthouse\")\r\n  |> range(start: v.timeRangeStart, stop: v.timeRangeStop)\r\n  |> filter(fn: (r) => r[\"_measurement\"] == \"first-contentful-paint-score\")\r\n  |> filter(fn: (r) => r[\"_field\"] == \"first-contentful-paint-score\")\r\n  |> filter(fn: (r) => r[\"host\"] == \"host1\")\r\n  |> filter(fn: (r) => r[\"url\"] == \"${url}\")",
          "refId": "A"
        }
      ],
      "title": "First Contentful Paint (FCP)",
      "type": "timeseries"
    },
    {
      "datasource": null,
      "description": "First Meaningful Paint measures when the primary content of a page is visible.",
      "fieldConfig": {
        "defaults": {
          "color": {
            "mode": "palette-classic"
          },
          "custom": {
            "axisLabel": "",
            "axisPlacement": "auto",
            "barAlignment": 0,
            "drawStyle": "line",
            "fillOpacity": 0,
            "gradientMode": "none",
            "hideFrom": {
              "legend": false,
              "tooltip": false,
              "viz": false
            },
            "lineInterpolation": "linear",
            "lineWidth": 1,
            "pointSize": 5,
            "scaleDistribution": {
              "type": "linear"
            },
            "showPoints": "auto",
            "spanNulls": false,
            "stacking": {
              "group": "A",
              "mode": "none"
            },
            "thresholdsStyle": {
              "mode": "off"
            }
          },
          "mappings": [],
          "thresholds": {
            "mode": "absolute",
            "steps": [
              {
                "color": "green",
                "value": null
              },
              {
                "color": "red",
                "value": 80
              }
            ]
          }
        },
        "overrides": []
      },
      "gridPos": {
        "h": 8,
        "w": 12,
        "x": 12,
        "y": 18
      },
      "id": 22,
      "options": {
        "legend": {
          "calcs": [],
          "displayMode": "list",
          "placement": "bottom"
        },
        "tooltip": {
          "mode": "single"
        }
      },
      "targets": [
        {
          "query": "from(bucket: \"lighthouse\")\r\n  |> range(start: v.timeRangeStart, stop: v.timeRangeStop)\r\n  |> filter(fn: (r) => r[\"_measurement\"] == \"first-meaningful-paint-score\")\r\n  |> filter(fn: (r) => r[\"_field\"] == \"first-meaningful-paint-score\")\r\n  |> filter(fn: (r) => r[\"host\"] == \"host1\")\r\n  |> filter(fn: (r) => r[\"url\"] == \"${url}\")",
          "refId": "A"
        }
      ],
      "title": "First Meaningful Paint",
      "type": "timeseries"
    },
    {
      "datasource": null,
      "fieldConfig": {
        "defaults": {
          "color": {
            "mode": "continuous-RdYlGr",
            "seriesBy": "last"
          },
          "custom": {
            "axisGridShow": true,
            "axisLabel": "",
            "axisPlacement": "left",
            "barAlignment": 0,
            "drawStyle": "line",
            "fillOpacity": 0,
            "gradientMode": "none",
            "hideFrom": {
              "legend": false,
              "tooltip": false,
              "viz": false
            },
            "lineInterpolation": "linear",
            "lineStyle": {
              "fill": "solid"
            },
            "lineWidth": 1,
            "pointSize": 5,
            "scaleDistribution": {
              "type": "linear"
            },
            "showPoints": "auto",
            "spanNulls": false,
            "stacking": {
              "group": "A",
              "mode": "none"
            },
            "thresholdsStyle": {
              "mode": "off"
            }
          },
          "displayName": "Speed Index",
          "mappings": [],
          "max": 1,
          "min": 0,
          "noValue": "null",
          "thresholds": {
            "mode": "absolute",
            "steps": [
              {
                "color": "green",
                "value": null
              },
              {
                "color": "red",
                "value": 80
              }
            ]
          },
          "unit": "locale"
        },
        "overrides": []
      },
      "gridPos": {
        "h": 8,
        "w": 12,
        "x": 0,
        "y": 26
      },
      "id": 18,
      "options": {
        "legend": {
          "calcs": [
            "min",
            "max",
            "mean"
          ],
          "displayMode": "table",
          "placement": "bottom"
        },
        "tooltip": {
          "mode": "single"
        }
      },
      "targets": [
        {
          "query": "from(bucket: \"lighthouse\")\r\n  |> range(start: v.timeRangeStart, stop: v.timeRangeStop)\r\n  |> filter(fn: (r) => r[\"_measurement\"] == \"speed-index-score\")\r\n  |> filter(fn: (r) => r[\"_field\"] == \"speed-index-score\")\r\n  |> filter(fn: (r) => r[\"host\"] == \"host1\")\r\n  |> filter(fn: (r) => r[\"url\"] == \"${url}\")",
          "refId": "A"
        }
      ],
      "title": "Speed Index",
      "type": "timeseries"
    },
    {
      "datasource": null,
      "description": "Interactive marks the time at which the page is fully interactive.",
      "fieldConfig": {
        "defaults": {
          "color": {
            "mode": "palette-classic"
          },
          "custom": {
            "axisLabel": "",
            "axisPlacement": "auto",
            "barAlignment": 0,
            "drawStyle": "line",
            "fillOpacity": 0,
            "gradientMode": "none",
            "hideFrom": {
              "legend": false,
              "tooltip": false,
              "viz": false
            },
            "lineInterpolation": "linear",
            "lineWidth": 1,
            "pointSize": 5,
            "scaleDistribution": {
              "type": "linear"
            },
            "showPoints": "auto",
            "spanNulls": false,
            "stacking": {
              "group": "A",
              "mode": "none"
            },
            "thresholdsStyle": {
              "mode": "off"
            }
          },
          "mappings": [],
          "thresholds": {
            "mode": "absolute",
            "steps": [
              {
                "color": "green",
                "value": null
              },
              {
                "color": "red",
                "value": 80
              }
            ]
          }
        },
        "overrides": []
      },
      "gridPos": {
        "h": 8,
        "w": 12,
        "x": 12,
        "y": 26
      },
      "id": 24,
      "options": {
        "legend": {
          "calcs": [],
          "displayMode": "list",
          "placement": "bottom"
        },
        "tooltip": {
          "mode": "single"
        }
      },
      "targets": [
        {
          "query": "from(bucket: \"lighthouse\")\r\n  |> range(start: v.timeRangeStart, stop: v.timeRangeStop)\r\n  |> filter(fn: (r) => r[\"_measurement\"] == \"interactive-score\")\r\n  |> filter(fn: (r) => r[\"_field\"] == \"interactive-score\")\r\n  |> filter(fn: (r) => r[\"host\"] == \"host1\")\r\n  |> filter(fn: (r) => r[\"url\"] == \"${url}\")",
          "refId": "A"
        }
      ],
      "title": "Time to Interactive",
      "type": "timeseries"
    },
    {
      "collapsed": false,
      "datasource": null,
      "gridPos": {
        "h": 1,
        "w": 24,
        "x": 0,
        "y": 34
      },
      "id": 2,
      "panels": [],
      "title": "Other",
      "type": "row"
    },
    {
      "datasource": null,
      "fieldConfig": {
        "defaults": {
          "color": {
            "mode": "palette-classic"
          },
          "custom": {
            "axisLabel": "",
            "axisPlacement": "auto",
            "barAlignment": 0,
            "drawStyle": "line",
            "fillOpacity": 0,
            "gradientMode": "none",
            "hideFrom": {
              "legend": false,
              "tooltip": false,
              "viz": false
            },
            "lineInterpolation": "linear",
            "lineWidth": 1,
            "pointSize": 5,
            "scaleDistribution": {
              "type": "linear"
            },
            "showPoints": "auto",
            "spanNulls": false,
            "stacking": {
              "group": "A",
              "mode": "none"
            },
            "thresholdsStyle": {
              "mode": "off"
            }
          },
          "mappings": [],
          "thresholds": {
            "mode": "absolute",
            "steps": [
              {
                "color": "green",
                "value": null
              },
              {
                "color": "red",
                "value": 80
              }
            ]
          }
        },
        "overrides": []
      },
      "gridPos": {
        "h": 8,
        "w": 8,
        "x": 0,
        "y": 35
      },
      "id": 26,
      "options": {
        "legend": {
          "calcs": [],
          "displayMode": "list",
          "placement": "bottom"
        },
        "tooltip": {
          "mode": "single"
        }
      },
      "targets": [
        {
          "query": "from(bucket: \"lighthouse\")\r\n  |> range(start: v.timeRangeStart, stop: v.timeRangeStop)\r\n  |> filter(fn: (r) => r[\"_measurement\"] == \"dom-size-score\")\r\n  |> filter(fn: (r) => r[\"_field\"] == \"dom-size-score\")\r\n  |> filter(fn: (r) => r[\"host\"] == \"host1\")\r\n  |> filter(fn: (r) => r[\"url\"] == \"${url}\")",
          "refId": "A"
        }
      ],
      "title": "DOM nodes count score",
      "type": "timeseries"
    },
    {
      "datasource": null,
      "fieldConfig": {
        "defaults": {
          "color": {
            "mode": "palette-classic"
          },
          "custom": {
            "axisLabel": "",
            "axisPlacement": "auto",
            "barAlignment": 0,
            "drawStyle": "line",
            "fillOpacity": 0,
            "gradientMode": "none",
            "hideFrom": {
              "legend": false,
              "tooltip": false,
              "viz": false
            },
            "lineInterpolation": "linear",
            "lineWidth": 1,
            "pointSize": 5,
            "scaleDistribution": {
              "type": "linear"
            },
            "showPoints": "auto",
            "spanNulls": false,
            "stacking": {
              "group": "A",
              "mode": "none"
            },
            "thresholdsStyle": {
              "mode": "off"
            }
          },
          "mappings": [],
          "thresholds": {
            "mode": "absolute",
            "steps": [
              {
                "color": "green",
                "value": null
              },
              {
                "color": "red",
                "value": 80
              }
            ]
          }
        },
        "overrides": []
      },
      "gridPos": {
        "h": 8,
        "w": 8,
        "x": 8,
        "y": 35
      },
      "id": 28,
      "options": {
        "legend": {
          "calcs": [],
          "displayMode": "list",
          "placement": "bottom"
        },
        "tooltip": {
          "mode": "single"
        }
      },
      "targets": [
        {
          "query": "from(bucket: \"lighthouse\")\r\n  |> range(start: v.timeRangeStart, stop: v.timeRangeStop)\r\n  |> filter(fn: (r) => r[\"_measurement\"] == \"dom-max-depth\")\r\n  |> filter(fn: (r) => r[\"_field\"] == \"dom-max-depth\")\r\n  |> filter(fn: (r) => r[\"host\"] == \"host1\")\r\n  |> filter(fn: (r) => r[\"url\"] == \"${url}\")",
          "refId": "A"
        }
      ],
      "title": "DOM max nodes depth",
      "type": "timeseries"
    },
    {
      "datasource": null,
      "fieldConfig": {
        "defaults": {
          "color": {
            "mode": "palette-classic"
          },
          "custom": {
            "axisLabel": "",
            "axisPlacement": "auto",
            "barAlignment": 0,
            "drawStyle": "line",
            "fillOpacity": 0,
            "gradientMode": "none",
            "hideFrom": {
              "legend": false,
              "tooltip": false,
              "viz": false
            },
            "lineInterpolation": "linear",
            "lineWidth": 1,
            "pointSize": 5,
            "scaleDistribution": {
              "type": "linear"
            },
            "showPoints": "auto",
            "spanNulls": false,
            "stacking": {
              "group": "A",
              "mode": "none"
            },
            "thresholdsStyle": {
              "mode": "off"
            }
          },
          "mappings": [],
          "thresholds": {
            "mode": "absolute",
            "steps": [
              {
                "color": "green",
                "value": null
              },
              {
                "color": "red",
                "value": 80
              }
            ]
          }
        },
        "overrides": []
      },
      "gridPos": {
        "h": 8,
        "w": 8,
        "x": 16,
        "y": 35
      },
      "id": 30,
      "options": {
        "legend": {
          "calcs": [],
          "displayMode": "list",
          "placement": "bottom"
        },
        "tooltip": {
          "mode": "single"
        }
      },
      "targets": [
        {
          "query": "from(bucket: \"lighthouse\")\r\n  |> range(start: v.timeRangeStart, stop: v.timeRangeStop)\r\n  |> filter(fn: (r) => r[\"_measurement\"] == \"dom-max-child-elements\")\r\n  |> filter(fn: (r) => r[\"_field\"] == \"dom-max-child-elements\")\r\n  |> filter(fn: (r) => r[\"host\"] == \"host1\")\r\n  |> filter(fn: (r) => r[\"url\"] == \"${url}\")",
          "refId": "A"
        }
      ],
      "title": "DOM Max child nodes",
      "type": "timeseries"
    },
    {
      "datasource": null,
      "fieldConfig": {
        "defaults": {
          "color": {
            "mode": "palette-classic"
          },
          "custom": {
            "axisLabel": "",
            "axisPlacement": "auto",
            "barAlignment": 0,
            "drawStyle": "line",
            "fillOpacity": 0,
            "gradientMode": "none",
            "hideFrom": {
              "legend": false,
              "tooltip": false,
              "viz": false
            },
            "lineInterpolation": "linear",
            "lineWidth": 1,
            "pointSize": 5,
            "scaleDistribution": {
              "type": "linear"
            },
            "showPoints": "auto",
            "spanNulls": false,
            "stacking": {
              "group": "A",
              "mode": "none"
            },
            "thresholdsStyle": {
              "mode": "off"
            }
          },
          "mappings": [],
          "thresholds": {
            "mode": "absolute",
            "steps": [
              {
                "color": "green",
                "value": null
              },
              {
                "color": "red",
                "value": 80
              }
            ]
          }
        },
        "overrides": []
      },
      "gridPos": {
        "h": 8,
        "w": 12,
        "x": 0,
        "y": 43
      },
      "id": 32,
      "options": {
        "legend": {
          "calcs": [],
          "displayMode": "list",
          "placement": "bottom"
        },
        "tooltip": {
          "mode": "single"
        }
      },
      "targets": [
        {
          "query": "from(bucket: \"lighthouse\")\r\n  |> range(start: v.timeRangeStart, stop: v.timeRangeStop)\r\n  |> filter(fn: (r) => r[\"_measurement\"] == \"total-byte-weight-score\")\r\n  |> filter(fn: (r) => r[\"_field\"] == \"total-byte-weight-score\")\r\n  |> filter(fn: (r) => r[\"host\"] == \"host1\")\r\n  |> filter(fn: (r) => r[\"url\"] == \"${url}\")",
          "refId": "A"
        }
      ],
      "title": "Total Bytes Downloaded",
      "type": "timeseries"
    },
    {
      "datasource": null,
      "fieldConfig": {
        "defaults": {
          "color": {
            "mode": "palette-classic"
          },
          "custom": {
            "axisLabel": "",
            "axisPlacement": "auto",
            "barAlignment": 0,
            "drawStyle": "line",
            "fillOpacity": 0,
            "gradientMode": "none",
            "hideFrom": {
              "legend": false,
              "tooltip": false,
              "viz": false
            },
            "lineInterpolation": "linear",
            "lineWidth": 1,
            "pointSize": 5,
            "scaleDistribution": {
              "type": "linear"
            },
            "showPoints": "auto",
            "spanNulls": false,
            "stacking": {
              "group": "A",
              "mode": "none"
            },
            "thresholdsStyle": {
              "mode": "off"
            }
          },
          "mappings": [],
          "thresholds": {
            "mode": "absolute",
            "steps": [
              {
                "color": "green",
                "value": null
              },
              {
                "color": "red",
                "value": 80
              }
            ]
          }
        },
        "overrides": []
      },
      "gridPos": {
        "h": 8,
        "w": 12,
        "x": 12,
        "y": 43
      },
      "id": 34,
      "options": {
        "legend": {
          "calcs": [],
          "displayMode": "list",
          "placement": "bottom"
        },
        "tooltip": {
          "mode": "single"
        }
      },
      "title": "Network Requests",
      "type": "timeseries"
    }
  ],
  "schemaVersion": 31,
  "style": "dark",
  "tags": [],
  "templating": {
    "list": [
      {
        "allValue": null,
        "current": {
          "selected": false,
          "text": "http://www.exito.com/",
          "value": "http://www.exito.com/"
        },
        "description": "URL of Site to see",
        "error": null,
        "hide": 0,
        "includeAll": false,
        "label": "URL",
        "multi": false,
        "name": "url",
        "options": [
          {
            "selected": true,
            "text": "http://www.exito.com/",
            "value": "http://www.exito.com/"
          }
        ],
        "query": "http://www.exito.com/",
        "queryValue": "",
        "skipUrlSync": false,
        "type": "custom"
      }
    ]
  },
  "time": {
    "from": "now-1h",
    "to": "now"
  },
  "timepicker": {
    "hidden": false,
    "refresh_intervals": [
      "5s",
      "10s",
      "30s",
      "1m",
      "5m",
      "15m",
      "30m",
      "1h",
      "2h",
      "1d"
    ],
    "time_options": [
      "5m",
      "15m",
      "1h",
      "6h",
      "12h",
      "24h",
      "2d",
      "7d",
      "30d"
    ]
  },
  "timezone": "America/Bogota",
  "title": "Monitoring",
  "uid": "Xm4XkxK7k",
  "version": 1
}